vitesy/__init__.py
vitesy/client.py
vitesy/exceptions.py
vitesy_python_unofficial-0.1.0.dist-info/LICENSE
vitesy_python_unofficial-0.1.0.dist-info/METADATA
vitesy_python_unofficial-0.1.0.dist-info/WHEEL
vitesy_python_unofficial-0.1.0.dist-info/top_level.txt
vitesy_python_unofficial-0.1.0.dist-info/RECORD
