Metadata-Version: 2.1
Name: vitesy-python-unofficial
Version: 0.1.0
Summary: Unofficial Python SDK for Vitesy APIs
Home-page: https://github.com/yourusername/vitesy-python-unofficial
Author: Your Name
Author-email: Your Name <your.email@example.com>
License: MIT
Project-URL: Homepage, https://github.com/dgrassi1984/vitesy-python-unofficial
Project-URL: Bug-Tracker, https://github.com/dgrassi1984/vitesy-python-unofficial/issues
Keywords: vitesy,api,sdk,unofficial
Classifier: Development Status :: 3 - Alpha
Classifier: Intended Audience :: Developers
Classifier: License :: OSI Approved :: MIT License
Classifier: Programming Language :: Python :: 3
Classifier: Programming Language :: Python :: 3.7
Classifier: Programming Language :: Python :: 3.8
Classifier: Programming Language :: Python :: 3.9
Classifier: Programming Language :: Python :: 3.10
Classifier: Programming Language :: Python :: 3.11
Requires-Python: >=3.7
License-File: LICENSE
Requires-Dist: requests>=2.25.0
Requires-Dist: pydantic>=1.8.0
Provides-Extra: dev
Requires-Dist: pytest>=6.0; extra == "dev"
Requires-Dist: black>=21.0; extra == "dev"
Requires-Dist: isort>=5.0; extra == "dev"
Requires-Dist: mypy>=0.900; extra == "dev"
